ragdict/__init__.py
ragdict/rag_dict.py
ragdict-0.2.1.dist-info/METADATA
ragdict-0.2.1.dist-info/WHEEL
ragdict-0.2.1.dist-info/licenses/LICENSE
ragdict-0.2.1.dist-info/RECORD
