Metadata-Version: 2.4
Name: ragdict
Version: 0.2.1
Summary: A dictionary with fuzzy key matching using RAG and LLM
Project-URL: Homepage, https://github.com/freQuensy23-coder/RagDict
Project-URL: Bug Tracker, https://github.com/freQuensy23-coder/RagDict/issues
Author-email: freQuensy23-coder <your.email@example.com>
License-File: LICENSE
Classifier: License :: OSI Approved :: MIT License
Classifier: Operating System :: OS Independent
Classifier: Programming Language :: Python :: 3
Requires-Python: >=3.8
Requires-Dist: numpy>=1.20.0
Requires-Dist: openai>=1.0.0
